trnlp/LICENSE.txt
trnlp/__init__.py
trnlp/cleaner.py
trnlp/constant.py
trnlp/controler.py
trnlp/file_prossesing.py
trnlp/finder.py
trnlp/helper.py
trnlp/morphology.py
trnlp/spelling_corrector.py
trnlp/tokenization.py
trnlp/data/__init__.py
trnlp/data/ana_sozluk.txt
trnlp/data/ascii_to_str_dict.pickle
trnlp/data/dafNoun.pbz2
trnlp/data/dafVerb.pbz2
trnlp/data/freq_dict.pbz2
trnlp/data/gen_tr_lex.pbz2
trnlp/data/infNoun.pbz2
trnlp/data/infVerb.pbz2
trnlp/data/kisaltma_sozluk.txt
trnlp/data/ozel_sozluk.txt
trnlp/data/prop_tr_lex.pbz2
trnlp/data/short_tr_lex.pbz2
trnlp/data/shortlist.pickle
trnlp/data/suffix_tables.py
trnlp/deasciifier/Asciidecoder.py
trnlp/deasciifier/__init__.py
trnlp/generator/__init__.py
trnlp/generator/createLexiconsPickle.py
trnlp/generator/createSuffixPickle.py
trnlp/token_data/__init__.py
trnlp/token_data/data.py
trnlp/token_data/punctuation.py
trnlp/unidecoder/__init__.py
trnlp/unidecoder/x000.py
trnlp/unidecoder/x001.py
trnlp/unidecoder/x002.py
trnlp/unidecoder/x003.py
trnlp/unidecoder/x004.py
trnlp/unidecoder/x005.py
trnlp/unidecoder/x006.py
trnlp/unidecoder/x007.py
trnlp/unidecoder/x009.py
trnlp/unidecoder/x00a.py
trnlp/unidecoder/x00b.py
trnlp/unidecoder/x00c.py
trnlp/unidecoder/x00d.py
trnlp/unidecoder/x00e.py
trnlp/unidecoder/x00f.py
trnlp/unidecoder/x010.py
trnlp/unidecoder/x011.py
trnlp/unidecoder/x012.py
trnlp/unidecoder/x013.py
trnlp/unidecoder/x014.py
trnlp/unidecoder/x015.py
trnlp/unidecoder/x016.py
trnlp/unidecoder/x017.py
trnlp/unidecoder/x018.py
trnlp/unidecoder/x01d.py
trnlp/unidecoder/x01e.py
trnlp/unidecoder/x01f.py
trnlp/unidecoder/x020.py
trnlp/unidecoder/x021.py
trnlp/unidecoder/x022.py
trnlp/unidecoder/x023.py
trnlp/unidecoder/x024.py
trnlp/unidecoder/x025.py
trnlp/unidecoder/x026.py
trnlp/unidecoder/x027.py
trnlp/unidecoder/x028.py
trnlp/unidecoder/x029.py
trnlp/unidecoder/x02a.py
trnlp/unidecoder/x02c.py
trnlp/unidecoder/x02e.py
trnlp/unidecoder/x02f.py
trnlp/unidecoder/x030.py
trnlp/unidecoder/x031.py
trnlp-0.2.2a1.dist-info/LICENSE.txt
trnlp-0.2.2a1.dist-info/METADATA
trnlp-0.2.2a1.dist-info/WHEEL
trnlp-0.2.2a1.dist-info/top_level.txt
trnlp-0.2.2a1.dist-info/RECORD
