Metadata-Version: 2.1
Name: trnlp
Version: 0.2.2a1
Summary: Türkçe doğal dil işleme araçları
Home-page: https://github.com/brolin59/trnlp
Author: Esat Mahmut Bayol
Author-email: trnlp2020@gmail.com
License: GNU General Public License v3 (GPLv3)
Download-URL: https://github.com/brolin59/trnlp/archive/0.2.2a1.tar.gz
Project-URL: Documentation, https://github.com/brolin59/trnlp/wiki
Project-URL: Source, https://github.com/brolin59/trnlp/tree/master/trnlp
Keywords: türkçe,doğal,dil,işleme,nlp,ddi,trnlp
Platform: UNKNOWN
Classifier: Development Status :: 3 - Alpha
Classifier: Intended Audience :: Developers
Classifier: Intended Audience :: Education
Classifier: Intended Audience :: Science/Research
Classifier: Intended Audience :: Information Technology
Classifier: Environment :: Win32 (MS Windows)
Classifier: License :: OSI Approved :: GNU General Public License v3 (GPLv3)
Classifier: Programming Language :: Python :: 3.7
Requires-Python: >=3.5
